README.md
setup.py
console_progress_bar.egg-info/PKG-INFO
console_progress_bar.egg-info/SOURCES.txt
console_progress_bar.egg-info/dependency_links.txt
console_progress_bar.egg-info/not-zip-safe
console_progress_bar.egg-info/top_level.txt
progressBar/__init__.py